[{"id":5880791,"name":"‘Āmanave","alt":["'Amanave","'Āmanave","Amanave"],"lon":-170.82944,"lat":-14.33,"pop":0},{"id":5880820,"name":"‘Aoa","alt":["Aoa"],"lon":-170.58389,"lat":-14.26556,"pop":466},{"id":5880751,"name":"A‘asufou","lon":-170.76389,"lat":-14.32028,"pop":0},{"id":5880784,"name":"A‘oloaufou","alt":["Aoloaufou"],"lon":-170.76778,"lat":-14.31972,"pop":0},{"id":5880752,"name":"Aasu","alt":["A`asu"],"lon":-170.75833,"lat":-14.2975,"pop":0},{"id":5880749,"name":"Afao","lon":-170.79917,"lat":-14.33667,"pop":0},{"id":5880755,"name":"Āfono","alt":["Afono"],"lon":-170.65083,"lat":-14.26417,"pop":527},{"id":5880744,"name":"Afulei","lon":-170.62389,"lat":-14.28,"pop":0},{"id":5880743,"name":"Aganoa","lon":-170.57917,"lat":-14.27944,"pop":0},{"id":5880781,"name":"Agugulu","lon":-170.82167,"lat":-14.33556,"pop":0},{"id":5880764,"name":"Alao","lon":-170.56361,"lat":-14.2675,"pop":508},{"id":5880758,"name":"Alaufau","alt":["Aloafao"],"lon":-169.68073,"lat":-14.16705,"pop":0},{"id":5880773,"name":"Ālega","alt":["Alega"],"lon":-170.6375,"lat":-14.28528,"pop":0},{"id":5880757,"name":"Alofau","lon":-170.60222,"lat":-14.27917,"pop":465},{"id":5880789,"name":"Amalau (historical)","lon":-170.65833,"lat":-14.2575,"pop":0},{"id":5880793,"name":"Amaluia","lon":-170.79111,"lat":-14.33833,"pop":0},{"id":5880796,"name":"Amaua","lon":-170.62167,"lat":-14.27694,"pop":0},{"id":5880799,"name":"Āmouli","alt":["Amouli"],"lon":-170.5825,"lat":-14.27806,"pop":0},{"id":5880802,"name":"Amouli (historical)","lon":-169.49417,"lat":-14.27139,"pop":0},{"id":5880808,"name":"Anasosopo","lon":-170.66278,"lat":-14.28861,"pop":0},{"id":5880813,"name":"Anua","lon":-170.68778,"lat":-14.275,"pop":0},{"id":5880833,"name":"Aoloau","lon":-170.77,"lat":-14.31972,"pop":966},{"id":5880811,"name":"Aoloautuai (historical)","alt":["A`oloautuai","Aoloau"],"lon":-170.78,"lat":-14.30028,"pop":0},{"id":5880818,"name":"Asili","lon":-170.79556,"lat":-14.33556,"pop":0},{"id":5880826,"name":"Atu‘u","alt":["Atuu"],"lon":-170.68472,"lat":-14.27444,"pop":0},{"id":5880828,"name":"Aūa","alt":["Aua","`Ava Point"],"lon":-170.66389,"lat":-14.27611,"pop":2124},{"id":5880829,"name":"Auasi","alt":["Au`asi","`Au`asi"],"lon":-170.57444,"lat":-14.27667,"pop":0},{"id":5880835,"name":"Auma","alt":["A`uma"],"lon":-170.78639,"lat":-14.34083,"pop":0},{"id":5880836,"name":"Aumi","lon":-170.64667,"lat":-14.29194,"pop":0},{"id":5880837,"name":"Aunu‘u","alt":["Aunuu"],"lon":-170.56055,"lat":-14.2836,"pop":0},{"id":5880859,"name":"Autapini","lon":-170.6975,"lat":-14.27889,"pop":0},{"id":5880844,"name":"Auto","alt":["`Auto *"],"lon":-170.62694,"lat":-14.28306,"pop":0},{"id":5880860,"name":"Avaio","lon":-170.63083,"lat":-14.28528,"pop":0},{"id":5880849,"name":"Avau","lon":-170.69278,"lat":-14.31083,"pop":0},{"id":5881218,"name":"Etena - Jennings Residency","lon":-171.07476,"lat":-11.06028,"pop":0},{"id":5880889,"name":"Faalaaga (historical)","alt":["Fa`ala`aga"],"lon":-169.64175,"lat":-14.16985,"pop":0},{"id":5881222,"name":"Faalefu","alt":["Fa`alefu"],"lon":-170.58917,"lat":-14.26694,"pop":0},{"id":5881227,"name":"Faga","lon":-169.455,"lat":-14.21778,"pop":0},{"id":5881231,"name":"Faga‘alu","alt":["Fagaalu","Fangaalu"],"lon":-170.68361,"lat":-14.29639,"pop":0},{"id":5880921,"name":"Faga‘itua","alt":["Fagaitua"],"lon":-170.61194,"lat":-14.27194,"pop":0},{"id":5880931,"name":"Fagalea","alt":["Fagale`a","Fangalea"],"lon":-170.71861,"lat":-14.28917,"pop":0},{"id":5881236,"name":"Fagalele","lon":-170.78444,"lat":-14.34667,"pop":0},{"id":5880946,"name":"Fagali‘i","alt":["Fagalii","Fangali`i"],"lon":-170.82472,"lat":-14.31222,"pop":0},{"id":5880948,"name":"Fagamalo","alt":["Fangamalo"],"lon":-170.80889,"lat":-14.30361,"pop":0},{"id":5881239,"name":"Fagamalo (historical)","lon":-169.50222,"lat":-14.25056,"pop":0},{"id":5881233,"name":"Fagamutu","lon":-170.805,"lat":-14.33611,"pop":0},{"id":5881225,"name":"Faganeanea","alt":["Fagane`ane`a"],"lon":-170.68889,"lat":-14.30611,"pop":0},{"id":5881243,"name":"Fagasā","alt":["Fagasa","Fungasar"],"lon":-170.71861,"lat":-14.29083,"pop":0},{"id":5881242,"name":"Fagatele","alt":["Fangatele"],"lon":-170.72278,"lat":-14.29333,"pop":0},{"id":5881241,"name":"Fagatogo","alt":["Fanga Tonga","Фагатого"],"lon":-170.69,"lat":-14.2825,"pop":1868},{"id":5881101,"name":"Faiava","alt":["Fai`ava"],"lon":-169.61746,"lat":-14.16069,"pop":0},{"id":5881249,"name":"Failolo","alt":["Fa`ilolo"],"lon":-170.82583,"lat":-14.33361,"pop":0},{"id":5881254,"name":"Faleāsao","alt":["Faleasao","Faleasau"],"lon":-169.51278,"lat":-14.2222,"pop":0},{"id":5881224,"name":"Faleniu","lon":-170.74444,"lat":-14.3325,"pop":3200},{"id":5881169,"name":"Falili","lon":-170.78,"lat":-14.35639,"pop":0},{"id":5881265,"name":"Fatumafuti","lon":-170.67722,"lat":-14.30139,"pop":0},{"id":5881017,"name":"Fitiuta","alt":["Aga`e","FTI","Fiti'uta","Fiti`uta Village","Fiti‘uta"],"lon":-169.42493,"lat":-14.21675,"pop":0},{"id":5881270,"name":"Fogaau","lon":-170.58806,"lat":-14.28194,"pop":0},{"id":5881266,"name":"Fogāgogo","alt":["Fogagogo"],"lon":-170.72222,"lat":-14.34278,"pop":0},{"id":5881275,"name":"Fogausa","lon":-170.60361,"lat":-14.28611,"pop":0},{"id":5881274,"name":"Fusi","lon":-169.51028,"lat":-14.24361,"pop":0},{"id":5881278,"name":"Fusi","lon":-170.70028,"lat":-14.27889,"pop":0},{"id":5881602,"name":"Futiga","lon":-170.75417,"lat":-14.35333,"pop":0},{"id":5881287,"name":"Ili‘ili","alt":["Iliili","`Ili`ili"],"lon":-170.74694,"lat":-14.35167,"pop":0},{"id":5881273,"name":"Itū‘au","alt":["Ituau"],"lon":-170.76639,"lat":-14.34778,"pop":0},{"id":5881425,"name":"Lalomoana","lon":-169.6235,"lat":-14.16571,"pop":0},{"id":5881294,"name":"Lalopua","lon":-170.69528,"lat":-14.27528,"pop":0},{"id":5881300,"name":"Lauagae","alt":["Lau`agae"],"lon":-170.56861,"lat":-14.25444,"pop":0},{"id":5881364,"name":"Lauli‘i","lon":-170.65306,"lat":-14.29222,"pop":0},{"id":5881356,"name":"Lauliifou","alt":["Lauli`ifou"],"lon":-170.65889,"lat":-14.29361,"pop":0},{"id":5881334,"name":"Lauliituai","alt":["Lauli`ituai"],"lon":-170.65278,"lat":-14.29167,"pop":0},{"id":5881342,"name":"Leloaloa","lon":-170.67806,"lat":-14.27222,"pop":546},{"id":5881347,"name":"Leone","lon":-170.785,"lat":-14.34389,"pop":4050},{"id":5881354,"name":"Lepine","lon":-170.72778,"lat":-14.32389,"pop":0},{"id":5881358,"name":"Lepisi (historical)","lon":-169.47583,"lat":-14.26806,"pop":0},{"id":5881353,"name":"Lepua (historical)","lon":-169.6079,"lat":-14.17726,"pop":0},{"id":5881365,"name":"Lepula (historical)","lon":-169.43611,"lat":-14.21917,"pop":0},{"id":5881373,"name":"Letula (historical)","lon":-169.44389,"lat":-14.21917,"pop":0},{"id":5881368,"name":"Leusoali‘i","alt":["Leusoalii"],"lon":-169.42111,"lat":-14.22611,"pop":0},{"id":5881391,"name":"Luamaa (historical)","alt":["Luama`a *"],"lon":-169.42028,"lat":-14.25333,"pop":0},{"id":5881396,"name":"Lumā","alt":["Luma"],"lon":-169.51472,"lat":-14.23167,"pop":0},{"id":5881407,"name":"Mafafa (historical)","lon":-169.64392,"lat":-14.16829,"pop":0},{"id":5881411,"name":"Maia","lon":-169.42833,"lat":-14.21944,"pop":0},{"id":5881410,"name":"Malaeimi","lon":-170.73389,"lat":-14.32278,"pop":1261},{"id":5881413,"name":"Malaeloa","lon":-170.76722,"lat":-14.34417,"pop":0},{"id":5881409,"name":"Malaeloa/Aitulagi","lon":-170.76784,"lat":-14.33861,"pop":633},{"id":5881401,"name":"Malaeloa/Ituau","lon":-170.76722,"lat":-14.34722,"pop":717},{"id":5881423,"name":"Malaloa","lon":-170.6925,"lat":-14.28083,"pop":0},{"id":5881430,"name":"Maloata","alt":["Moloata"],"lon":-170.81472,"lat":-14.30944,"pop":0},{"id":5881433,"name":"Mapusaga","lon":-170.74389,"lat":-14.33,"pop":0},{"id":5881442,"name":"Mapusagafou","lon":-170.75278,"lat":-14.33056,"pop":2052},{"id":5881446,"name":"Masausi","alt":["Masa`usi"],"lon":-170.60417,"lat":-14.26472,"pop":0},{"id":5881444,"name":"Masefau","lon":-170.63056,"lat":-14.25917,"pop":0},{"id":5881482,"name":"Matu‘u","alt":["Matuu"],"lon":-170.68389,"lat":-14.30361,"pop":0},{"id":5881497,"name":"Maupua (historical)","lon":-170.57083,"lat":-14.25361,"pop":0},{"id":5881496,"name":"Mesepa","lon":-170.74444,"lat":-14.33139,"pop":552},{"id":11695139,"name":"Motu o Manu","lon":-168.16592,"lat":-14.54313,"pop":4},{"id":5881535,"name":"Nu‘uuli","alt":["Nuuuli"],"lon":-170.6975,"lat":-14.31583,"pop":0},{"id":5881533,"name":"Nua","lon":-170.80583,"lat":-14.33306,"pop":0},{"id":5881556,"name":"Oa (historical)","lon":-170.64139,"lat":-14.25861,"pop":0},{"id":5881544,"name":"Ofu","alt":["OFU"],"lon":-169.67851,"lat":-14.17117,"pop":254},{"id":5881561,"name":"Oge (historical)","lon":-169.60989,"lat":-14.18352,"pop":0},{"id":5881565,"name":"Ogefao","lon":-170.57778,"lat":-14.25389,"pop":0},{"id":5881564,"name":"Ogegase (historical)","lon":-170.58417,"lat":-14.25833,"pop":0},{"id":5881567,"name":"Olosega","alt":["Olosega Village"],"lon":-169.62425,"lat":-14.17699,"pop":0},{"id":5881583,"name":"Onenoa","alt":["`Onenoa"],"lon":-170.57972,"lat":-14.25667,"pop":0},{"id":5881577,"name":"Oneoneloa","lon":-170.69444,"lat":-14.31278,"pop":0},{"id":5881587,"name":"Ottoville","alt":["otobil","오토빌"],"lon":-170.72972,"lat":-14.33472,"pop":0},{"id":5881590,"name":"Pagai","lon":-170.60528,"lat":-14.275,"pop":0},{"id":5881576,"name":"Pago Pago","alt":["PPG","Paga-Paga","Pago-Pago","PagoPago","Pagopago","Pagó Pagó","Panko Panko","Paqo Paqo","baghw baghw","pa guo pa guo","pa ko pa ko","pago pago","pagopago","pagw pagw","pako pako","pango pango","Πάγκο Πάγκο","Пага-Пага","Паго Паго","Паго-Паго","Пагопаго","Պագո Պագո","פאגו פאגו","باغو باغو","پاگو پاگو","पांगो पांगो","பாகோ பாகோ","ปาโกปาโก","პაგო-პაგო","パゴパゴ","帕果帕果","파고 파고","파고파고"],"lon":-170.7025,"lat":-14.27806,"pop":11500},{"id":5881623,"name":"Pava‘ia‘i","alt":["Pavaiai"],"lon":-170.75083,"lat":-14.34083,"pop":0},{"id":5881622,"name":"Poloa","lon":-170.83278,"lat":-14.32167,"pop":0},{"id":5881193,"name":"Puapua","lon":-170.7719,"lat":-14.34472,"pop":0},{"id":5880998,"name":"Sa‘ilele","alt":["Sailele"],"lon":-170.59639,"lat":-14.26222,"pop":0},{"id":5881007,"name":"Samoi (historical)","lon":-169.6745,"lat":-14.16087,"pop":0},{"id":5881001,"name":"Satala","lon":-170.69222,"lat":-14.27124,"pop":0},{"id":5881010,"name":"Saua (historical)","lon":-169.42,"lat":-14.24139,"pop":0},{"id":5880984,"name":"Se‘etaga","alt":["Se`etana","Seetaga","Seetuga"],"lon":-170.81056,"lat":-14.33056,"pop":0},{"id":5881018,"name":"Si‘ufaga","alt":["Siufaga"],"lon":-170.58528,"lat":-14.27917,"pop":0},{"id":5881020,"name":"Si‘ufaga","alt":["Siufaga"],"lon":-170.69889,"lat":-14.275,"pop":0},{"id":5881043,"name":"Si‘ufaga","alt":["Siufaga"],"lon":-169.51167,"lat":-14.24083,"pop":0},{"id":5881026,"name":"Sili","lon":-169.61962,"lat":-14.16442,"pop":0},{"id":5880735,"name":"Sogi","lon":-170.78361,"lat":-14.35417,"pop":0},{"id":5881165,"name":"Ta`ū","alt":["Opoun","TAV","Ta`u","Ta`ue Village","Ta`ü Village","Tau"],"lon":-169.51444,"lat":-14.23361,"pop":873},{"id":5881201,"name":"Tafalau (historical)","lon":-169.61085,"lat":-14.16935,"pop":0},{"id":5880963,"name":"Tafananai","lon":-170.66285,"lat":-14.28788,"pop":0},{"id":5880812,"name":"Tafeta","lon":-170.75167,"lat":-14.32556,"pop":0},{"id":5881192,"name":"Tāfuna","alt":["Tafuna","Тафуна"],"lon":-170.72,"lat":-14.33583,"pop":7988},{"id":5881189,"name":"Tafunafou","lon":-170.73083,"lat":-14.32917,"pop":0},{"id":5881190,"name":"Tagapofu","lon":-170.6825,"lat":-14.30333,"pop":0},{"id":5881168,"name":"Taputimu","lon":-170.77306,"lat":-14.36028,"pop":741},{"id":5881150,"name":"Taulaga","lon":-171.08833,"lat":-11.05528,"pop":37},{"id":5881120,"name":"Tō‘aga (historical)","alt":["To`aga","Toaga (historical)"],"lon":-169.6535,"lat":-14.17602,"pop":0},{"id":5881113,"name":"Tuafanua (historical)","lon":-169.65324,"lat":-14.16762,"pop":0},{"id":5881109,"name":"Tuaolo","alt":["Tuae`olo","Tuä`olo"],"lon":-170.75917,"lat":-14.31944,"pop":0},{"id":5881098,"name":"Tula","lon":-170.56417,"lat":-14.25806,"pop":370},{"id":5881093,"name":"Tulauta (historical)","alt":["Tulotu"],"lon":-170.5675,"lat":-14.2575,"pop":0},{"id":5880737,"name":"Utulei","alt":["Утулеи"],"lon":-170.68306,"lat":-14.28694,"pop":683},{"id":5881066,"name":"Utuloa","lon":-170.61722,"lat":-14.26444,"pop":0},{"id":5881060,"name":"Utumea","alt":["Utumea East"],"lon":-170.56917,"lat":-14.27583,"pop":0},{"id":5881061,"name":"Utumea","lon":-170.81389,"lat":-14.33361,"pop":0},{"id":5881055,"name":"Utumea East","lon":-170.56833,"lat":-14.27583,"pop":0},{"id":5881057,"name":"Utumea West","lon":-170.81722,"lat":-14.33417,"pop":0},{"id":5880970,"name":"Utusia","alt":["Utusi`a"],"lon":-170.61861,"lat":-14.27583,"pop":0},{"id":5880956,"name":"Vaiala","lon":-170.77861,"lat":-14.34611,"pop":0},{"id":5880944,"name":"Vailoatai","alt":["Vailoa"],"lon":-170.7808,"lat":-14.3534,"pop":1144},{"id":5880891,"name":"Vaitogi","lon":-170.73796,"lat":-14.35259,"pop":1436},{"id":5880884,"name":"Vasaaiga","alt":["Vasa`aeiga","Vasa`äiga"],"lon":-170.68611,"lat":-14.30556,"pop":0},{"id":5880881,"name":"Vatia","lon":-170.67528,"lat":-14.255,"pop":0}]