[{"id":3042271,"name":"Andreas","lon":-4.43333,"lat":54.36667,"pop":0},{"id":3042267,"name":"Ballabeg","lon":-4.68333,"lat":54.1,"pop":0},{"id":8504401,"name":"Ballacannell","lon":-4.40496,"lat":54.2173,"pop":0},{"id":11550888,"name":"Ballacarnane Beg","lon":-4.61512,"lat":54.26227,"pop":0},{"id":3042265,"name":"Ballakinnag","lon":-4.55,"lat":54.33333,"pop":0},{"id":3042264,"name":"Ballasalla","lon":-4.62962,"lat":54.0959,"pop":0},{"id":8468983,"name":"Ballaugh","lon":-4.54456,"lat":54.31193,"pop":0},{"id":11550882,"name":"Barregarrow","alt":["Bayr Garroo"],"lon":-4.58272,"lat":54.26252,"pop":0},{"id":3042259,"name":"Bride","lon":-4.38921,"lat":54.38256,"pop":0},{"id":3042255,"name":"Castletown","alt":["Baile Chaistil","Balley Chashtal","Castletoun","Kasltaun","Kasltaunas","Каслтаун"],"lon":-4.65365,"lat":54.07445,"pop":3100},{"id":3042251,"name":"Colby","lon":-4.70592,"lat":54.09665,"pop":289},{"id":3042247,"name":"Cranstal","alt":["Cranstall"],"lon":-4.36947,"lat":54.3956,"pop":0},{"id":3042246,"name":"Cregneish","alt":["Cregneash","Creneash"],"lon":-4.76841,"lat":54.06961,"pop":0},{"id":11591723,"name":"Cronk-y-Voddy","lon":-4.60894,"lat":54.24093,"pop":0},{"id":3042245,"name":"Crosby","lon":-4.56667,"lat":54.18333,"pop":0},{"id":3042244,"name":"Dalby","alt":["Delbee"],"lon":-4.72923,"lat":54.16879,"pop":0},{"id":3042241,"name":"Derbyhaven","alt":["Camys y Ree"],"lon":-4.62353,"lat":54.07646,"pop":0},{"id":3042238,"name":"Dog Mills","lon":-4.38333,"lat":54.35,"pop":0},{"id":3042237,"name":"Douglas","alt":["Daglas","Daglasa","Daglasas","Daglaso","Doolish","Douglas pa Isle of Man","Douglas på Isle of Man","Douglas  Isle of Man","Dubh Lios","Duglas","Duqlas","Ntanklas","Port Douglas","dagalasa","daglasa","dagurasu","daklas","dao ge la si","deogeulleoseu","duglasi","dwghlas","dwglas","taklacu","Ντάγκλας","Даглас","Дуглас","Дъглас","דאגלס","دوغلاس","دوگلاس","ڈگلس","डग्लस","ਡਗਲਸ","டக்லசு","ดักลาส","დუგლასი","ダグラス","道格拉斯","더글러스"],"lon":-4.48333,"lat":54.15,"pop":26218},{"id":3042231,"name":"Foxdale","alt":["Forsdal"],"lon":-4.61667,"lat":54.16667,"pop":0},{"id":3042229,"name":"Glen Maye","alt":["Glion Meay","Glion Muigh"],"lon":-4.7,"lat":54.18333,"pop":0},{"id":3042224,"name":"Jurby","lon":-4.52199,"lat":54.35941,"pop":0},{"id":3042221,"name":"Kirk Braddan","alt":["Kirk Braddon","Saint Braddon"],"lon":-4.51667,"lat":54.16667,"pop":0},{"id":3042220,"name":"Kirkmichael","lon":-4.58748,"lat":54.28562,"pop":0},{"id":3042217,"name":"Laxey","alt":["Laksaa","Laksi","Лакси"],"lon":-4.39985,"lat":54.23017,"pop":1768},{"id":3042213,"name":"Lezayre","lon":-4.41667,"lat":54.31667,"pop":0},{"id":11550883,"name":"Little London","lon":-4.57984,"lat":54.24406,"pop":0},{"id":3042210,"name":"Maughold","alt":["Saint Maughold"],"lon":-4.31844,"lat":54.29877,"pop":0},{"id":3042201,"name":"Onchan","alt":["Conchan","Kione Droghad","Onkan","Onkanas","Онкан"],"lon":-4.45324,"lat":54.17329,"pop":0},{"id":11550885,"name":"Orrisdale","lon":-4.5752,"lat":54.30481,"pop":0},{"id":3042199,"name":"Patrick","alt":["Saint Patrick"],"lon":-4.69417,"lat":54.20447,"pop":0},{"id":3042198,"name":"Peel","alt":["Pil","Purt na hInse","Purt ny h-Inshey","Purt ny hInshey","Pylas","Пил"],"lon":-4.69099,"lat":54.22209,"pop":5374},{"id":3042196,"name":"Port Erin","alt":["Port-Ehrin","Порт-Эрин"],"lon":-4.75099,"lat":54.08487,"pop":3530},{"id":3042195,"name":"Port Saint Mary","lon":-4.73858,"lat":54.07405,"pop":0},{"id":3042193,"name":"Port Soderick","alt":["Purt Soderick"],"lon":-4.54113,"lat":54.12865,"pop":0},{"id":3042192,"name":"Ramsey","alt":["Ramsi","Ramsis","Rhumsaa","Рамси"],"lon":-4.38526,"lat":54.32273,"pop":7845},{"id":3042189,"name":"Ronaldsway","lon":-4.61667,"lat":54.08333,"pop":0},{"id":3042186,"name":"Saint Johns","alt":["Balley Keeill Eoin"],"lon":-4.63333,"lat":54.2,"pop":0},{"id":3042185,"name":"Saint Marks","alt":["Saint Mark"],"lon":-4.6,"lat":54.13333,"pop":0},{"id":3042182,"name":"Santon","alt":["Saint Anne"],"lon":-4.58333,"lat":54.11667,"pop":0},{"id":11550884,"name":"Shoughlaige-e-Caine","lon":-4.58662,"lat":54.25309,"pop":0},{"id":3042174,"name":"Sulby","lon":-4.47968,"lat":54.32283,"pop":0},{"id":3042170,"name":"Union Mills","alt":["Mullin Doway","Mwyllin Doo Aah"],"lon":-4.52019,"lat":54.16957,"pop":0}]