[{"id":387981,"name":"‘Ashīsh ad Dawḩah","alt":["`Ashish ad Dawhah","عَشِيش اَلدَّوْحَة"],"lon":47.84222,"lat":29.38528,"pop":0},{"id":388048,"name":"‘Ashīsh al Jahrā’","alt":["Ashish al Jahrah","Ashīsh al Jahrah","`Ashish al Jahra'","عَشِيش اَلْجَهْرَاء"],"lon":47.67778,"lat":29.31722,"pop":0},{"id":285384,"name":"‘Urayfijān","alt":["Arefjan","`Araifjan","`Urayfijan","عُرَيْفِجَان","‘Araifjān"],"lon":48.18333,"lat":28.9,"pop":0},{"id":285375,"name":"‘Ushaysh al Jahrā’","alt":["`Ushaysh al Jahra'","عُشَيْش اَلْجَهْرَاء"],"lon":47.66389,"lat":29.31583,"pop":0},{"id":285866,"name":"Abraq Khayţān","alt":["Abrag Khitan","Abrag Khīţān","Abrak Khetan","Abraq Haytan","Abraq Khaitan","Abraq Khaytan","Abraq Khetan","Abraq Khitan","Abraq Khīţān","Khaitan","Khitan","Koetan","aabraq khaytan","أَبْرَق خَيْطَان"],"lon":47.96889,"lat":29.2925,"pop":0},{"id":11593501,"name":"Abu Al Hasaniya","lon":48.11355,"lat":29.19076,"pop":1350},{"id":11593499,"name":"Abu Fatira","lon":48.10278,"lat":29.19746,"pop":1240},{"id":285864,"name":"Abū Ḩulayfah","alt":["Abi Huleifa","Abu Halaifa","Abu Halaifah","Abu Halifah","Abu Hulaifa","Abu Hulaifah","Abu Hulayfah","Abu Ḩulaifah","Abu-Hleifa","Halaifa","aabu hulayfat","abw hlyft","أَبُو حُلَيْفَة","ابو حليفة"],"lon":48.12611,"lat":29.13222,"pop":0},{"id":285857,"name":"Ad Da‘īyah","alt":["Ad Da`iyah","Al Diya","Al Edeiya","اَلدَّعِيَّة"],"lon":47.98333,"lat":29.33333,"pop":0},{"id":387952,"name":"Ad Da‘īyah","alt":["Ad Da`iyah","Daiya","الدعية","اَلدَّعِيَّة"],"lon":48.01472,"lat":29.35806,"pop":0},{"id":387941,"name":"Ad Dasht","alt":["aaldasht","اَلدَّشْت"],"lon":48.31389,"lat":29.4625,"pop":0},{"id":285856,"name":"Ad Dasmah","alt":["Ad Dasma'","Ad Dasmā’","Dasma","Dasmah","aaldasmat","اَلدَّسْمَة"],"lon":48.00139,"lat":29.365,"pop":17585},{"id":285855,"name":"Ad Dawḩah","alt":["Ad Dawhah","Al Doha","Dauha","Doha","aaldawhat","اَلدَّوْحَة"],"lon":47.81,"lat":29.36778,"pop":0},{"id":388052,"name":"Ad Dawḩah","alt":["Ad Dawhah","aaldawhat","اَلدَّوْحَة"],"lon":47.81194,"lat":29.31444,"pop":0},{"id":285853,"name":"Aḑ Ḑibā‘īyah","alt":["Ad Diba`iyah","Al Adhaba-iyah","Al-Dhubaiyah","Dhuba`iyah","Dhuba‘iyah","Dubayeiha","اَلضِّبَاعِيَّة"],"lon":48.16667,"lat":28.93333,"pop":0},{"id":388102,"name":"Aḑ Ḑubā‘īyah","alt":["Ad Duba`iyah","اَلضُّبَاعِيَّة"],"lon":48.20722,"lat":28.92361,"pop":0},{"id":388088,"name":"Al ‘Abbāsīyah","alt":["Al `Abbasiyah","اَلْعَبَّاسِيَّة"],"lon":47.93111,"lat":29.25028,"pop":0},{"id":285848,"name":"Al ‘Abdalīyah","alt":["Al `Abdaliyah","اَلْعَبْدَلِيَّة"],"lon":47.70611,"lat":29.0425,"pop":0},{"id":8300014,"name":"Al ‘Adan","alt":["Al `Adan","Al-Adan"],"lon":48.0685,"lat":29.23274,"pop":0},{"id":388014,"name":"Al ‘Adīlīyah","alt":["Al `Adiliyah","Al `Udayliyah","Al ‘Udaylīyah","اَلْعَدِيلِيَّة"],"lon":47.97694,"lat":29.32056,"pop":0},{"id":414978,"name":"Al ‘Arfajīyah","alt":["Al `Arfajiyah","العرفجية","اَلْعَرْفَجِيَّة"],"lon":48.09556,"lat":29.70028,"pop":0},{"id":388071,"name":"Al ‘Āriḑīyah","alt":["Al Aridiyah","Al `Aridiyah","Al Āridīyah","اَلْعَارِضِيَّة"],"lon":47.875,"lat":29.28417,"pop":0},{"id":387948,"name":"Al ‘Awāzim","alt":["Al `Awazim","اَلْعَوَازِم"],"lon":48.385,"lat":29.42028,"pop":0},{"id":285766,"name":"Al ‘Udaylīyah","alt":["Al `Udayliyah","اَلْعُدَيْلِيَّة"],"lon":47.96667,"lat":29.3,"pop":0},{"id":414979,"name":"Al ‘Ulaymīyah","alt":["Al Alaymah","Al `Ulaymiyah","Al-`Alaimah","Al-‘Alaimah","العليميه","اَلْعُلَيْمِيَّة"],"lon":48.11417,"lat":29.68806,"pop":0},{"id":388064,"name":"Al ‘Umarīyah","alt":["Al `Umariyah","اَلْعُمَرِيَّة"],"lon":47.95333,"lat":29.29333,"pop":0},{"id":285764,"name":"Al ‘Uqaylah","alt":["Al `Uqaylah","Al `Uqlah","Al ‘Uqlah","Ugla","`Uqaila","`Uqallah","`Uqlah","اَلْعُقَيْلَة","‘Uqaila","‘Uqallah","‘Uqlah"],"lon":48.09472,"lat":29.17778,"pop":0},{"id":285845,"name":"Al Ad‘amī","alt":["Al Ad`ami","اَلأَدْعَمِي"],"lon":48.26667,"lat":28.81667,"pop":0},{"id":285839,"name":"Al Aḩmadī","alt":["Ahmad","Ahmadi","Ahmedi","Al Ahmadi","Al Aħmadi","aalaahmadi","alahmdy","الاحمدي","اَلأَحْمَدِي"],"lon":48.08389,"lat":29.07694,"pop":637411},{"id":387964,"name":"Al Badawīyah","alt":["Al Badawiyah","aalbadawiat","اَلْبَدَوِيَّة"],"lon":48.11778,"lat":29.08139,"pop":0},{"id":285823,"name":"Al Bhar","alt":["aalbhar","اَلْبْهَر"],"lon":47.83333,"lat":29.38333,"pop":0},{"id":412799,"name":"Al Bid‘","alt":["Al Bid`","اَلْبِدْع"],"lon":48.08778,"lat":29.31222,"pop":0},{"id":285822,"name":"Al Bida‘","alt":["Al Bid`","Al Bida`","Al Biddah","Al Bid‘","Al-Bidde","Bad'ah","Bad’ah","اَلْبِدَع"],"lon":48.08694,"lat":29.3025,"pop":0},{"id":387938,"name":"Al Bulţ","alt":["Al Bult","aalbult","اَلْبُلْط"],"lon":48.28139,"lat":29.4575,"pop":0},{"id":285811,"name":"Al Faḩāḩīl","alt":["Al Fahahil","Al Fuhaihil","Al Fuhayhil","Al Fuħaiħil","Al Fuḩayḩīl","Al Ifhaihil","Al-Fahaheel","Al-Fahahil","Fahaheel","Fahahil","Fahaihil","Fahaihīl","Fahayhil","Fahāhīl","Faḩayḩīl","Fuhayhil","Fuḩayḩīl","aalfuhayhil","alfhahyl","الفحاحيل","اَلْفُحَيْحِيل"],"lon":48.13028,"lat":29.0825,"pop":68290},{"id":285815,"name":"Al Farwānīyah","alt":["Al Farwania","Al Farwaniyah","Al-Farawaniyah","Al-Farwaniyyah","Farwaniah","Farwaniyyeh","aalfarwaniat","اَلْفَرْوَانِيَّة"],"lon":47.95861,"lat":29.2775,"pop":86525},{"id":285813,"name":"Al Fayḩā’","alt":["Al Fayha'","Fayha","اَلْفَيْحَاء"],"lon":47.97583,"lat":29.33639,"pop":0},{"id":285812,"name":"Al Finţās","alt":["Al Fantas","Al Fintas","Al Fintass","Al Fintās","Fantas","Fantass","Fanţās","Finatus","Fintas","Fintass","Finţās","Funtas","Funtás","aalfintas","alfntas","الفنطاس","اَلْفِنْطَاس"],"lon":48.12111,"lat":29.17389,"pop":23071},{"id":285810,"name":"Al Funayţīs","alt":["Al Fanaitis","Al Funaitis","Al Funaytis","Al-Finaitees","Fanaitis","Fneitees","Fraitsass","Funaitis","Funaitís","Funaytis","Funayţīs","aalfunaytis","alfnytys","الفنيطيس","اَلْفُنَيْطِيس"],"lon":48.10167,"lat":29.22528,"pop":1878},{"id":285809,"name":"Al Ḩadīqah","alt":["Al Hadeeqa","Al Hadiqah","aalhadiqat","اَلْحَدِيقَة"],"lon":47.98333,"lat":29.33333,"pop":0},{"id":285803,"name":"Al Ḩujayjah","alt":["Al Hujayjah","Al-Hijajah","Hagaija","Haqaija","Haqaijah","Hugaija","aalhujayjat","alhjyjt","الحجيجة","اَلْحُجَيْجَة"],"lon":48.13111,"lat":29.65472,"pop":0},{"id":387957,"name":"Al Jābirīyah","alt":["Al Jabiriyah","aaljabiriat","اَلْجَابِرِيَّة"],"lon":48.02361,"lat":29.32222,"pop":0},{"id":285799,"name":"Al Jahrā’","alt":["Al Jahara","Al Jahra","Al Jahra'","Al Jahrah","Al-Jaharah","Iahara","Jahra Village","Jahrah","اَلْجَهْرَاء"],"lon":47.65806,"lat":29.3375,"pop":24281},{"id":388012,"name":"Al Khālidīyah","alt":["Al Khalidiyah","aalkhalidiat","اَلْخَالِدِيَّة"],"lon":47.96556,"lat":29.32806,"pop":0},{"id":387937,"name":"Al Khiḑr","alt":["Al Khidr","aalkhidr","اَلْخِضْر"],"lon":48.28833,"lat":29.46444,"pop":0},{"id":285790,"name":"Al Khīrān","alt":["Al Khiran","aalkhiran","اَلْخِيرَان"],"lon":48.39028,"lat":28.65111,"pop":0},{"id":387913,"name":"Al Khuwaysāt","alt":["Al Khuwaysat","aalkhuaysat","اَلْخُوَيْسَات"],"lon":47.71111,"lat":29.40333,"pop":0},{"id":285783,"name":"Al Maghāsil","alt":["Al Maghasil","aalmaghasil","almghasl","المغاسل","اَلْمَغَاسِل"],"lon":48.09444,"lat":29.74194,"pop":0},{"id":285782,"name":"Al Mahbūlah","alt":["Al Mahbulah","Al-Mahabulah","Al-Mahabūlah","Mahboola","aalmahbulat","almhbwlt","المهبولة","اَلْمَهْبُولَة"],"lon":48.13028,"lat":29.145,"pop":18178},{"id":285778,"name":"Al Manqaf","alt":["Al Manjaf","Al-Mangaf","Manqaf","aalmanqaf","almnqf","المنقف","اَلْمَنْقَف"],"lon":48.13278,"lat":29.09611,"pop":39025},{"id":387997,"name":"Al Manşūrīyah","alt":["Al Mansuriyah","aalmansuriat","اَلْمَنْصُورِيَّة"],"lon":47.98056,"lat":29.35556,"pop":0},{"id":285776,"name":"Al Maqwa‘","alt":["Al Magwa","Al Maqwa`","Magwa","Majiwah","Majīwah","Maqwa","Maqwah","اَلْمَقْوَع"],"lon":47.98333,"lat":29.16667,"pop":0},{"id":387962,"name":"Al Masīlah","alt":["Al Masilah","Al Massilah","Al Massīlah","Messila","aalmasilat","almsylt","المسيلة","اَلْمَسِيلَة"],"lon":48.07972,"lat":29.26194,"pop":0},{"id":388024,"name":"Al Mīnā’","alt":["Al Mina'","اَلْمِينَاء"],"lon":47.93611,"lat":29.32972,"pop":0},{"id":388036,"name":"Al Murayţibah","alt":["Al Muraytibah","aalmuraytibat","اَلْمُرَيْطِبَة"],"lon":47.6525,"lat":29.36472,"pop":0},{"id":387994,"name":"Al Murqāb","alt":["Al Murqab","aalmurqab","اَلْمُرْقَاب"],"lon":47.97806,"lat":29.36556,"pop":0},{"id":387954,"name":"Al Qādisīyah","alt":["Al Qadisiyah","aalqadisiat","اَلْقَادِسِيَّة"],"lon":48.00694,"lat":29.35028,"pop":0},{"id":388018,"name":"Al Qādisīyah","alt":["Al Qadisiyah","aalqadisiat","اَلْقَادِسِيَّة"],"lon":47.985,"lat":29.3475,"pop":0},{"id":285770,"name":"Al Qash‘ānīyah","alt":["Al Qash`aniya","Al Qash`aniyah","Al Qash‘aniya","القشعانية","اَلْقَشْعَانِيَّة"],"lon":47.75866,"lat":29.98337,"pop":0},{"id":387990,"name":"Al Qiblah","alt":["aalqiblat","اَلْقِبْلَة"],"lon":47.97167,"lat":29.37361,"pop":0},{"id":285768,"name":"Al Qulay‘ah","alt":["Al Qulay`ah","اَلْقُلَيْعَة"],"lon":48.27472,"lat":28.86583,"pop":0},{"id":7329410,"name":"Al Qurayn","lon":48.0757,"lat":29.2043,"pop":0},{"id":7329409,"name":"Al Quşūr","lon":48.0726,"lat":29.21748,"pop":0},{"id":285760,"name":"Al Wafrah","alt":["aalwafrat","اَلْوَفْرَة"],"lon":47.93056,"lat":28.63917,"pop":10017},{"id":387897,"name":"Al Wafrah","alt":["aalwafrat","اَلْوَفْرَة"],"lon":48.05306,"lat":28.55417,"pop":0},{"id":388056,"name":"Al Yarmūk","alt":["Al Yarmuk","aalyarmuk","اَلْيَرْمُوك"],"lon":47.9675,"lat":29.30778,"pop":0},{"id":11593497,"name":"Al-Masayel","lon":48.08862,"lat":29.2393,"pop":2458},{"id":285750,"name":"An Nāmī","alt":["An Nami","aalnaami","اَلنَّامِي"],"lon":48.36444,"lat":28.63972,"pop":0},{"id":285747,"name":"An Nijfah","alt":["Al Mijifa","Al Nijifa","Al-Najafa","aalnijfat","اَلنِّجْفَة"],"lon":48.07583,"lat":29.24639,"pop":0},{"id":285746,"name":"An Nuqayyāt","alt":["Al-Nigaiyat","An Niggaiyat","An Nugayyat","An Nugayyāt","An Nuqay`at","An Nuqayyat","An Nuqay‘āt","aalnuqayaat","اَلنُّقَيَّات"],"lon":48.19861,"lat":28.94306,"pop":0},{"id":285506,"name":"An Nuqrah","alt":["Muqrah","Nigra","Nugra","Nuqrah","aalnuqrat","اَلنُّقْرَة"],"lon":48.01056,"lat":29.3375,"pop":0},{"id":388015,"name":"An Nuzhah","alt":["aalnuzhat","اَلنُّزْهَة"],"lon":47.98972,"lat":29.34167,"pop":0},{"id":388065,"name":"Ar Rābiyah","alt":["Ar Rabiyah","aalraabiat","اَلرَّابِيَة"],"lon":47.93306,"lat":29.295,"pop":36447},{"id":285734,"name":"Ar Rawḑah","alt":["Ar Raudha","Ar Rawdah","Rowda","aalrawdat","اَلرَّوْضَة"],"lon":48.00139,"lat":29.32472,"pop":0},{"id":387956,"name":"Ar Rawḑah","alt":["Ar Rawdah","aalrawdat","اَلرَّوْضَة"],"lon":48.00639,"lat":29.31583,"pop":0},{"id":388055,"name":"Ar Rayy","alt":["aalray","اَلرَّيّ"],"lon":47.93417,"lat":29.30917,"pop":0},{"id":285728,"name":"Ar Riqqah","alt":["Al-Riqqah","Reqqa","aalriqat","alrqt","الرقة","اَلرِّقَّة"],"lon":48.09472,"lat":29.14583,"pop":52068},{"id":285726,"name":"Ar Rumaythīyah","alt":["Ar Rumaythiyah","Rumaithiya","aalrumaythiat","alrmythyt","الرميثية","اَلرُّمَيْثِيَّة"],"lon":48.07417,"lat":29.31167,"pop":58135},{"id":285711,"name":"Aş Şabāḩīyah","alt":["Al-Sabahiyah","As Sabahiyah","Subahiya","aalsabahiat","alsbahyt","الصباحية","اَلصَّبَاحِيَّة"],"lon":48.10806,"lat":29.10583,"pop":0},{"id":387995,"name":"Aş Şāliḩīyah","alt":["As Salihiyah","aalsaalihiat","اَلصَّالِحِيَّة"],"lon":47.96889,"lat":29.36333,"pop":0},{"id":285704,"name":"As Sālimīyah","alt":["Ad Dumna","Ad Dumnah","As Salimiyah","As-Salimiyah","As-Sālimiyah","Dimnah","Salimiyah","Salmiya","Salmiyah","Salmiyyeh","aalsaalimiat","alsalmyt","السالمية","اَلسَّالِمِيَّة"],"lon":48.07611,"lat":29.33389,"pop":147649},{"id":285698,"name":"Aş Şulaybīkhāt","alt":["Al-Sulaibikhat","As Sulaybikhat","Sulaibikhat","Suleibikhat","aalsulaybikhat","اَلصُّلَيْبِيخَات"],"lon":47.83583,"lat":29.31528,"pop":0},{"id":388060,"name":"As Surrah","alt":["aalsurat","اَلسُّرَّة"],"lon":47.99,"lat":29.27528,"pop":0},{"id":387953,"name":"Ash Sha‘b","alt":["Ash Sha`b","Sha'ab","Sha’ab","الشعب","اَلشَّعْب"],"lon":48.025,"lat":29.34694,"pop":0},{"id":285722,"name":"Ash Shadādīyah","alt":["Ash Shadadiyah","aalshadadiat","اَلشَّدَادِيَّة"],"lon":47.84556,"lat":29.26806,"pop":0},{"id":285721,"name":"Ash Shāmīyah","alt":["Al Shamiya","Ash Shamiyah","Shamiya","Shamiyah","Shamiyeh","Shamiyyeh","Shamīyah","aalshaamiat","اَلشَّامِيَّة"],"lon":47.96167,"lat":29.34722,"pop":13762},{"id":387989,"name":"Ash Sharq","alt":["aalsharq","اَلشَّرْق"],"lon":47.98722,"lat":29.37944,"pop":0},{"id":285716,"name":"Ash Shu‘aybah","alt":["Al-Shuaiba","As Shu`aiba","As Shu‘aiba","Ash Shu`aiba","Ash Shu`aybah","Ash Shu‘aiba","Sha'iba","Shaab","Shaabah","Shauiba","Sha’iba","Shi'aibah","Shi’aibah","Shu`aybah","Shua'ibah","Shuaiba","Shua’ibah","Shu‘aybah","اَلشُّعَيْبَة"],"lon":48.1375,"lat":29.04111,"pop":0},{"id":387939,"name":"Ash Shubaykah","alt":["aalshubaykat","اَلشُّبَيْكَة"],"lon":48.29917,"lat":29.43167,"pop":0},{"id":285713,"name":"Ash Shuwaykh","alt":["Al Shuwaikh","Bandar Shuwaik","Bandar Shuwaikh","Bandar ash Shuwaykh","Bander Shweikh","Port Shuwaikh","Shuwaikh","Shuwaikh Port","Shuwoikh","aalshuwaykh","اَلشُّوَيْخ"],"lon":47.94611,"lat":29.34361,"pop":0},{"id":384601,"name":"Aţ Ţawīl","alt":["At Tawil","aaltawil","اَلطَّوِيل"],"lon":47.90722,"lat":28.97861,"pop":0},{"id":285542,"name":"Az Zawr","alt":["Mina' Sa`ud","Mina' az Zawr","Mina' az-Zor","Minā’ az-Zor","Mīnā’ Sa‘ūd","Mīnā’ az Zawr","aalzawr","اَلزَّوْر"],"lon":48.37278,"lat":28.7375,"pop":0},{"id":285673,"name":"Az Zawr","alt":["Az Zaur","Az Zor","Failakka Village","Zor","aalzawr","اَلزَّوْر"],"lon":48.27472,"lat":29.4425,"pop":5750},{"id":285828,"name":"Bahra","alt":["Al Bahrah","Al Baḩrah","Al-Bahra","Bahrah","Baḩrah","aalbahrat","اَلْبَحْرَة"],"lon":47.86667,"lat":29.66667,"pop":0},{"id":285663,"name":"Bayān","alt":["Bajan","Bayan","bayan","byan","Баян","بيان","بَيَان"],"lon":48.04881,"lat":29.3032,"pop":30635},{"id":387951,"name":"Bunayd al Qār","alt":["Bunayd al Qar","bunayd aalqar","بُنَيْد اَلْقَار"],"lon":48.0025,"lat":29.37556,"pop":0},{"id":388021,"name":"Ḑāhiyat ‘Abd Allāh as Sālim","alt":["Dahiyat `Abd Allah as Salim","ضَاهِيَة عَبْد اَللَّٰه اَلسَّالِم"],"lon":47.98,"lat":29.35139,"pop":0},{"id":285654,"name":"Dant","alt":["dant","دَنْت"],"lon":48.11667,"lat":29.16667,"pop":0},{"id":285646,"name":"Ḑulay‘ Su‘ūd","alt":["Dhulai` Sa`ud","Dhulai‘ Sa‘ūd","Dulay` Sa`ud","Dulay` Su`ud","ضُلَيْع سُعُود","Ḑulay‘ Sa‘ūd"],"lon":48.11111,"lat":29.20111,"pop":0},{"id":285643,"name":"Duwaydāt","alt":["Duwaydat","duaydat","دُوَيْدَات"],"lon":48.39917,"lat":28.58278,"pop":0},{"id":285629,"name":"Ḩawallī","alt":["Hawali-nogra","Hawalli","Hawaly","hawaliy","hwly","حولي","حَوَلِّي"],"lon":48.02861,"lat":29.33278,"pop":164212},{"id":6942029,"name":"Highway of Death","alt":["Auto-put smrti","Autocesta smrti","Autoestrada da Morte","Autopista de la muerte","Autostrada della morte","Doedens motorvaeg","Dödens motorväg","Kuoleman moottoritie","Mirties greitkelis","Shosse smerti","Snelweg des Doods","sinohaiuei","tryq almwt","Ауто-пут смрти","Шоссе смерти","طريق الموت","死のハイウェイ"],"lon":47.6518,"lat":29.3842,"pop":0},{"id":8986155,"name":"Jaber Al Ali","alt":["XIJ"],"lon":48.0724,"lat":29.17082,"pop":0},{"id":285496,"name":"Jalīb ash Shuyūkh","alt":["Jalib ash Shuyukh","Qalib al Shuyukh","Qalib ash Shuyukh","Qalīb al Shuyūkh","Qalīb ash Shuyūkh","jalib aalshuyukh","جَلِيب اَلشُّيُوخ"],"lon":47.92417,"lat":29.25861,"pop":0},{"id":285604,"name":"Jalīb ash Shuyūkh","alt":["Jalib ash Shuyukh","Jleeb al Shuyoukh","jalib aalshuyukh","جَلِيب اَلشُّيُوخ"],"lon":47.93333,"lat":29.26667,"pop":0},{"id":285603,"name":"Janūb as Surrah","alt":["Janub as Surrah","South Surra","janub aalsurat","جَنُوب اَلسُّرَّة"],"lon":47.97806,"lat":29.26917,"pop":18496},{"id":388062,"name":"Janūb Khayţān","alt":["Janub Khaytan","janub khaytan","جَنُوب خَيْطَان"],"lon":47.97778,"lat":29.27222,"pop":0},{"id":285599,"name":"Ju‘aydān","alt":["Ju`aydan","Juaidan","جُعَيْدَان"],"lon":47.96722,"lat":28.96667,"pop":0},{"id":285590,"name":"Kayfān","alt":["Kaifan","Kayfan","Keefan","Kifan","Kīfān","kayfan","كَيْفَان"],"lon":47.96333,"lat":29.34139,"pop":0},{"id":285787,"name":"Kuwait City","alt":["Al Kuwait","Al Kuwayt","Al-Kuwait","Ciudad de Kuwait","Ehl'-Kuvejt","KWI","Koeweit","Kota Kuwait","Koveyit","Koweit","Koweït","Kuvaeyt","Kuvajt","Kuvajto","Kuvajturbo","Kuveitas","Kuväyt","Kuwait","Kuwait Stad","Kuwait by","Kuwait-Stadt","Kuwait-Urbo","Kuwayt","Kuweit","Kuwejt","Madinat al Kuwayt","Madinat al-Kuwait","Madīnat al Kuwayt","Pole tou Koubeit","aalkuayt","ke wei te shi","khuwet si ti","kuueto shi","kuweiteu","kuweiteusiti","kwwyt syty","mdyntalkwyt","Πόλη του Κουβέιτ","Эль-Кувейт","כווית סיטי","اَلْكُوَيْت","مدينة الكويت","คูเวตซิตี","クウェート市","科威特市","쿠웨이트","쿠웨이트시티"],"lon":47.97833,"lat":29.36972,"pop":60064},{"id":285556,"name":"Manīfah","alt":["Manifah","Munifah","Munīfah","manifat","مَنِيفَة"],"lon":48.08111,"lat":29.16083,"pop":0},{"id":387955,"name":"Maydān Ḩawallī","alt":["Maydan Hawalli","Sharq Hawalli","Sharq Ḩawallī","mydan hwly","sharq hawaliy","شَرْق حَوَلِّي","ميدان حولي"],"lon":48.0425,"lat":29.33611,"pop":0},{"id":11579278,"name":"Mazāri‘ al ‘Abdalī","alt":["Al `Abdali Farms","Al ‘Abdalī Farms","Mazari` al `Abdali","مزارع العبدلي"],"lon":47.72205,"lat":30.04219,"pop":0},{"id":387959,"name":"Mishrif","alt":["Mishref","Mushrif","mshrf","mushrif","مشرف","مُشْرِف"],"lon":48.05,"lat":29.28917,"pop":0},{"id":7329411,"name":"Mubārak al Kabīr","alt":["Mubarak Al-Kabeer"],"lon":48.08716,"lat":29.18979,"pop":0},{"id":412798,"name":"Qaşm Dasmān","alt":["Qasm Dasman","qasm dasman","قَصْم دَسْمَان"],"lon":47.99611,"lat":29.38,"pop":0},{"id":387943,"name":"Qullat Shujayr","alt":["qulat shujayr","قُلَّة شُجَيْر"],"lon":48.29972,"lat":29.45917,"pop":0},{"id":388058,"name":"Qurţubah","alt":["Qortuba","Qurtuba","Qurtubah","qurtubat","قُرْطُبَة"],"lon":47.98556,"lat":29.31222,"pop":0},{"id":412800,"name":"Şabāḩ as Sālim","alt":["Sabah as Salim","Sabah as Salim as Sabbah","sabah aalsaalim","Şabāḩ as Salim aş Sabbāḩ","صَبَاح اَلسَّالِم"],"lon":48.05722,"lat":29.25722,"pop":139163},{"id":10173853,"name":"Safat","lon":47.97298,"lat":29.37136,"pop":0},{"id":387958,"name":"Salwá","alt":["Sal'va","Salwa","salway","slwy","Сальва","سلوى","سَلْوَى"],"lon":48.07861,"lat":29.29583,"pop":40945},{"id":11427343,"name":"Sawabir","lon":47.98254,"lat":29.37549,"pop":0},{"id":285455,"name":"Shumaymah","alt":["shmymt","shumaymat","شميمة","شُمَيْمَة"],"lon":48.15056,"lat":29.61778,"pop":0},{"id":384610,"name":"Şubayḩīyah","alt":["Subayhiyah","subayhiat","صُبَيْحِيَّة"],"lon":47.91389,"lat":28.87944,"pop":0},{"id":285398,"name":"Umm Qaşbah","alt":["Umm Qasabah","Umm Qasbah","Umm Qaşabah","aum qasbat","أُمّ قَصْبَة"],"lon":48.16556,"lat":28.99222,"pop":0},{"id":414939,"name":"Umm Şiddah","alt":["Umm Siddah","aum sidat","أُمّ صِدَّة"],"lon":47.9925,"lat":29.36194,"pop":0},{"id":384614,"name":"Wārah","alt":["Warah","warat","وَارَة"],"lon":47.98222,"lat":28.99611,"pop":0}]